subscribear/__init__.py
subscribear/subscribear.py
subscribear-0.3.0.dist-info/LICENSE
subscribear-0.3.0.dist-info/METADATA
subscribear-0.3.0.dist-info/WHEEL
subscribear-0.3.0.dist-info/top_level.txt
subscribear-0.3.0.dist-info/RECORD
