Metadata-Version: 2.1
Name: subscribear
Version: 0.3.0
Summary: Will explain later ... 
Home-page: https://test.pypi.org/project/subscribear/
Author: nicuzs
Author-email: support@nicuzs.tech
License: MIT License
Requires-Dist: boto3 (>=1.10.37)
